repoGhost/__init__.py
repoGhost/cli.py
repoGhost-0.2.4.dist-info/LICENSE
repoGhost-0.2.4.dist-info/METADATA
repoGhost-0.2.4.dist-info/WHEEL
repoGhost-0.2.4.dist-info/entry_points.txt
repoGhost-0.2.4.dist-info/top_level.txt
repoGhost-0.2.4.dist-info/RECORD
