Metadata-Version: 2.1
Name: repoGhost
Version: 0.2.4
Summary: CLI tool to summarize code in a repo.
Author: George Stander
License: MIT License
Keywords: openai,repo,summaries,cli
Classifier: Programming Language :: Python :: 3
Classifier: License :: OSI Approved :: MIT License
Requires-Python: >=3.8
License-File: LICENSE
Requires-Dist: openai>=1.0.0
Requires-Dist: click>=8.0.0
Requires-Dist: tqdm>=4.65.0
Requires-Dist: pyperclip>=1.8.2
Requires-Dist: rich>=13.0.0
